{"_astro/do-more.b59f888e_Q7Klg.avif":{"expires":1718424620265},"_astro/default.4e32c3d9_1V4y4D.png":{"expires":1715578185055},"_astro/hero.e3ed522a_yRyz3.avif":{"expires":1718424620264},"_astro/vintage.5e0f956c_nt30r.avif":{"expires":1718424620264},"_astro/colors.ffce53b9_1ccwzz.avif":{"expires":1718424620264},"_astro/stickers.9710fe0a_hI5ib.avif":{"expires":1718424620265},"_astro/tools.6b4fe6d0_ZUyCGG.avif":{"expires":1718424620267},"_astro/g-and-l-streets.43fe8634_ZQKGnv.avif":{"expires":1750009528204},"_astro/caos.6bfe0e84_ZcBQGw.avif":{"expires":1718424620264},"_astro/hero.e3ed522a_ZJsFiu.avif":{"expires":1718424620264},"_astro/do-more.b59f888e_Z1yJEb4.avif":{"expires":1718424620265},"_astro/stickers.9710fe0a_Z289ke9.avif":{"expires":1718424620265},"_astro/vintage.5e0f956c_LCMsl.avif":{"expires":1718424620264},"_astro/colors.ffce53b9_Z1dERVK.avif":{"expires":1718424620264},"_astro/g-and-l-streets.43fe8634_Z2b6Vg3.avif":{"expires":1750009528204},"_astro/do-more.b59f888e_1De6n1.webp":{"expires":1718424620265},"_astro/stickers.9710fe0a_14OqjV.webp":{"expires":1718424620265},"_astro/vintage.5e0f956c_1azo2c.webp":{"expires":1718424620264},"_astro/colors.ffce53b9_1YiRBk.webp":{"expires":1718424620264},"_astro/tools.6b4fe6d0_1IK5zU.avif":{"expires":1718424620267},"_astro/do-more.b59f888e_ZLDj9j.webp":{"expires":1718424620265},"_astro/stickers.9710fe0a_Z1l2Yco.webp":{"expires":1718424620265},"_astro/vintage.5e0f956c_1yJ8u6.webp":{"expires":1718424620264},"_astro/colors.ffce53b9_ZqywU0.webp":{"expires":1718424620264},"_astro/tools.6b4fe6d0_Z8shEV.webp":{"expires":1718424620267},"_astro/do-more.b59f888e_ZulHV8.jpg":{"expires":1718424620265},"_astro/stickers.9710fe0a_Z29wkxY.jpg":{"expires":1718424620265},"_astro/vintage.5e0f956c_Zvh5XL.jpg":{"expires":1718424620264},"_astro/hero.e3ed522a_Z20Vm84.avif":{"expires":1718424620264},"_astro/colors.ffce53b9_um6vH.jpg":{"expires":1718424620264},"_astro/do-more.b59f888e_2wYJfI.jpg":{"expires":1718424620265},"_astro/tools.6b4fe6d0_2vQqBF.webp":{"expires":1718424620267},"_astro/stickers.9710fe0a_RO7CR.jpg":{"expires":1718424620265},"_astro/vintage.5e0f956c_XxX2Q.jpg":{"expires":1718424620264},"_astro/colors.ffce53b9_Z1xtz6n.jpg":{"expires":1718424620264},"_astro/tools.6b4fe6d0_Z2bUvNI.jpg":{"expires":1718424620267},"_astro/tools.6b4fe6d0_PpVn8.jpg":{"expires":1718424620267},"_astro/g-and-l-streets.43fe8634_ZM6avV.avif":{"expires":1750009528204},"_astro/caos.6bfe0e84_bwRKn.avif":{"expires":1718424620264},"_astro/caos.6bfe0e84_zttke.webp":{"expires":1718424620264},"_astro/caos.6bfe0e84_XDdM8.webp":{"expires":1718424620264},"_astro/caos.6bfe0e84_2pEUmV.jpg":{"expires":1718424620264},"_astro/caos.6bfe0e84_Z1aG9pn.jpg":{"expires":1718424620264},"_astro/hero.e3ed522a_ZqxN9P.avif":{"expires":1718424620264},"_astro/hero.e3ed522a_1lXTAN.webp":{"expires":1718424620264},"_astro/hero.e3ed522a_2CEIg.webp":{"expires":1718424620264},"_astro/hero.e3ed522a_Z1dP16j.webp":{"expires":1718424620264},"_astro/g-and-l-streets.43fe8634_2044XG.avif":{"expires":1750009528204},"_astro/g-and-l-streets.43fe8634_Z4EllK.webp":{"expires":1750009528204},"_astro/g-and-l-streets.43fe8634_Z1o0Aei.webp":{"expires":1750009528204},"_astro/hero.e3ed522a_lxwQU.webp":{"expires":1718424620264},"_astro/hero.e3ed522a_2rcnL5.jpg":{"expires":1718424620264},"_astro/hero.e3ed522a_Kxmpj.jpg":{"expires":1718424620264},"_astro/hero.e3ed522a_2w7elI.jpg":{"expires":1718424620264},"_astro/g-and-l-streets.43fe8634_auO.webp":{"expires":1750009528204},"_astro/hero.e3ed522a_Z1bU6ON.jpg":{"expires":1718424620264},"_astro/g-and-l-streets.43fe8634_Z2i1HNu.webp":{"expires":1750009528204},"_astro/g-and-l-streets.43fe8634_Z2lNqje.jpg":{"expires":1750009528204},"_astro/g-and-l-streets.43fe8634_12IG8V.jpg":{"expires":1750009528204},"_astro/g-and-l-streets.43fe8634_15sXoa.jpg":{"expires":1750009528204},"_astro/g-and-l-streets.43fe8634_1U4Lk.jpg":{"expires":1750009528204},"_astro/default.4e32c3d9_1aEIXL.png":{"expires":1718424620264},"_astro/save-the-date.2664e1de_Z2owKNA.avif":{"expires":1739924790554},"_astro/save-the-date.2664e1de_1mj87N.avif":{"expires":1739924790554},"_astro/save-the-date.2664e1de_2oX1oR.avif":{"expires":1739924790554},"_astro/save-the-date.2664e1de_ZyLJw6.avif":{"expires":1739924790554},"_astro/save-the-date.2664e1de_Z1BqpLP.webp":{"expires":1739924790554},"_astro/save-the-date.2664e1de_29pt9y.webp":{"expires":1739924790554},"_astro/save-the-date.2664e1de_Z1S7Lnj.webp":{"expires":1739924790554},"_astro/save-the-date.2664e1de_djAuE.webp":{"expires":1739924790554},"_astro/save-the-date.2664e1de_2gIcv3.png":{"expires":1739924790554},"_astro/save-the-date.2664e1de_A4b9h.png":{"expires":1739924790554},"_astro/save-the-date.2664e1de_1LaaWu.png":{"expires":1739924790554},"_astro/save-the-date.2664e1de_mfoRB.png":{"expires":1739924790554},"_astro/save-the-date.aaaeb5ee_Z1UTYa6.avif":{"expires":1740290119958},"_astro/save-the-date.aaaeb5ee_LApOY.avif":{"expires":1740290119958},"_astro/save-the-date.aaaeb5ee_Z9Pduk.avif":{"expires":1740290119958},"_astro/save-the-date.aaaeb5ee_1URFal.avif":{"expires":1740290119958},"_astro/save-the-date.aaaeb5ee_Z18ND8l.webp":{"expires":1740290119958},"_astro/save-the-date.aaaeb5ee_1yGKQJ.webp":{"expires":1740290119958},"_astro/save-the-date.aaaeb5ee_Cg7wq.webp":{"expires":1740290119958},"_astro/save-the-date.aaaeb5ee_Z2md7BP.webp":{"expires":1740290119958},"_astro/save-the-date.aaaeb5ee_ZarlH0.png":{"expires":1740290119958},"_astro/save-the-date.aaaeb5ee_Z1Iazxw.png":{"expires":1740290119958},"_astro/save-the-date.aaaeb5ee_2l8bBz.png":{"expires":1740290119958},"_astro/save-the-date.aaaeb5ee_Z20U48x.png":{"expires":1740290119958},"_astro/hero.a061ea73_Z4kJ3l.avif":{"expires":1750009528207},"_astro/hero.a061ea73_ZBO5pm.avif":{"expires":1750009528207},"_astro/hero.a061ea73_2hcH0c.avif":{"expires":1750009528207},"_astro/hero.a061ea73_1aO3FP.avif":{"expires":1750009528207},"_astro/hero.a061ea73_HKAXp.webp":{"expires":1750009528207},"_astro/hero.a061ea73_ahfBo.webp":{"expires":1750009528207},"_astro/hero.a061ea73_Z20S5LY.webp":{"expires":1750009528207},"_astro/hero.a061ea73_1WUoHA.webp":{"expires":1750009528207},"_astro/hero.a061ea73_Z1JPLFb.png":{"expires":1750009528207},"_astro/hero.a061ea73_Z1AUgAl.png":{"expires":1750009528207},"_astro/hero.a061ea73_Z2aetVH.png":{"expires":1750009528207},"_astro/hero.a061ea73_Z1dmJfd.png":{"expires":1750009528207},"_astro/dooley-pool.dd0459b5_U5Do6.avif":{"expires":1750009528206},"_astro/save-the-date.8e853e2e_2wTzoI.avif":{"expires":1750009528206},"_astro/dooley-pool.dd0459b5_ZofAtr.avif":{"expires":1750009528206},"_astro/save-the-date.8e853e2e_1UYSF6.avif":{"expires":1750009528206},"_astro/dooley-pool.dd0459b5_Z1oGckp.avif":{"expires":1750009528206},"_astro/save-the-date.8e853e2e_YyfkM.avif":{"expires":1750009528206},"_astro/dooley-pool.dd0459b5_Z1PDoHf.avif":{"expires":1750009528206},"_astro/dooley-pool.dd0459b5_1HbYpQ.webp":{"expires":1750009528206},"_astro/dooley-pool.dd0459b5_nPJxj.webp":{"expires":1750009528206},"_astro/dooley-pool.dd0459b5_ZBzQiE.webp":{"expires":1750009528206},"_astro/dooley-pool.dd0459b5_Z13x3Fu.webp":{"expires":1750009528206},"_astro/dooley-pool.dd0459b5_Z2siBIS.jpg":{"expires":1750009528206},"_astro/dooley-pool.dd0459b5_VeuIh.jpg":{"expires":1750009528206},"_astro/dooley-pool.dd0459b5_Z2cQODa.jpg":{"expires":1750009528206},"_astro/dooley-pool.dd0459b5_ZzEW29.jpg":{"expires":1750009528206},"_astro/save-the-date.8e853e2e_Z1YTYNt.avif":{"expires":1750009528206},"_astro/save-the-date.8e853e2e_Z1Kbdns.webp":{"expires":1750009528206},"_astro/save-the-date.8e853e2e_Z2m5T75.webp":{"expires":1750009528206},"_astro/save-the-date.8e853e2e_1LEAmx.webp":{"expires":1750009528206},"_astro/save-the-date.8e853e2e_Z1cNDLI.webp":{"expires":1750009528206},"_astro/save-the-date.8e853e2e_Z10FPNz.png":{"expires":1750009528206},"_astro/save-the-date.8e853e2e_ZmPTWl.png":{"expires":1750009528206},"_astro/save-the-date.8e853e2e_Z1nJhBb.png":{"expires":1750009528206},"_astro/save-the-date.8e853e2e_ZEAoxm.png":{"expires":1750009528206},"_astro/save-the-date.8e853e2e_sYxWY.avif":{"expires":1750009528206},"_astro/save-the-date.8e853e2e_Z1VRQyl.avif":{"expires":1750009528206},"_astro/save-the-date.8e853e2e_1g5SYJ.webp":{"expires":1750009528206},"_astro/save-the-date.8e853e2e_Z19LvwA.webp":{"expires":1750009528206},"_astro/save-the-date.8e853e2e_Z1eK0XU.png":{"expires":1750009528206},"_astro/save-the-date.8e853e2e_1MArcV.png":{"expires":1750009528206},"_astro/default.88c8d67a_Z1XO9sc.png":{"expires":1750009528204},"_astro/house.3f5122f0_23xcgR.avif":{"expires":1750010983680},"_astro/house.3f5122f0_JbWok.avif":{"expires":1750010983680},"_astro/house.3f5122f0_Z1H4YJ4.avif":{"expires":1750010983680},"_astro/house.3f5122f0_Z11kHAH.avif":{"expires":1750010983680},"_astro/house.3f5122f0_Z2exAvj.webp":{"expires":1750010983680},"_astro/house.3f5122f0_1wiiq5.webp":{"expires":1750010983680},"_astro/house.3f5122f0_ZTXDHj.webp":{"expires":1750010983680},"_astro/house.3f5122f0_ZeemyW.webp":{"expires":1750010983680},"_astro/house.3f5122f0_Z1r1AT8.jpg":{"expires":1750010983680},"_astro/house.3f5122f0_1Wvvy2.jpg":{"expires":1750010983680},"_astro/house.3f5122f0_Z14pgKo.jpg":{"expires":1750010983680},"_astro/house.3f5122f0_ZS3JqN.jpg":{"expires":1750010983680}}